pyiwn/__init__.py
pyiwn/constants.py
pyiwn/helpers.py
pyiwn/iwn.py
pyiwn-0.0.5.dist-info/AUTHORS.md
pyiwn-0.0.5.dist-info/LICENSE.txt
pyiwn-0.0.5.dist-info/METADATA
pyiwn-0.0.5.dist-info/WHEEL
pyiwn-0.0.5.dist-info/top_level.txt
pyiwn-0.0.5.dist-info/RECORD
