Metadata-Version: 2.1
Name: pyiwn
Version: 0.0.5
Summary: pyiwn -- A Python based API to access Indian language WordNets -- This API gives access to synsets, glosses, examples, lexico-semantic relations between synsets, ontology nodes for 18 Indian languages, viz., Assamese, Bangla, Bodo, Gujarati, Hindi, Kannada, Kashmiri, Konkani, Malayalam, Meitei (Manipuri), Marathi, Nepali, Odia, Punjabi, Sanskrit, Tamil, Telugu and Urdu. In future, it will also provide access to speech data for words, glosses examples in Hindi WordNet.
Home-page: https://github.com/riteshpanjwani/pyiwn
Author: Ritesh Panjwani
Author-email: riteshpanjwani@gmail.com
License: MIT
Keywords: wordnet,IndoWordNet,nlp,python,API
Platform: UNKNOWN
Requires-Dist: pandas
Requires-Dist: requests
